{
  "fmt": {
    "exclude": ["dist", "src/assets/prostate-map.svg"]
  },
  "lint": {},
  "imports": {
    "d3": "https://esm.sh/d3@7"
  },
  "tasks": {
    "fmt": "deno fmt",
    "lint": "deno lint",
    "test": "deno test",
    "copy-assets": "deno run --allow-read --allow-write scripts/copy-assets.ts",
    "bundle": "deno task copy-assets && deno bundle --platform browser -o demo/prostate-mri-map.bundle.js src/components/prostate-mri-map.ts",
    "dev": "deno task copy-assets && deno run --allow-net --allow-read https://deno.land/std@0.204.0/http/file_server.ts demo"
  }
}
